[
    {
        "date": "September 9, 2020",
        "district": "Statewide",
        "item_number": 1,
        "item_title": "CALL TO ORDER and ROLL CALL",
        "item_blurb": "",
        "subitem_number": "",
        "subitem_title": "",
        "subitem_blurb": "",
        "subitem_status": ""
    },
    {
        "date": "September 9, 2020",
        "district": "Statewide",
        "item_number": 2,
        "item_title": "VIRTUAL MEETING PROCEDURES",
        "item_blurb": "",
        "subitem_number": "",
        "subitem_title": "",
        "subitem_blurb": "",
        "subitem_status": ""
    },
    {
        "date": "September 9, 2020",
        "district": "Statewide",
        "item_number": 3,
        "item_title": "Agenda Changes",
        "item_blurb": "",
        "subitem_number": "",
        "subitem_title": "",
        "subitem_blurb": "",
        "subitem_status": ""
    },
    {
        "date": "September 9, 2020",
        "district": "Statewide",
        "item_number": 4,
        "item_title": "General Public Comment",
        "item_blurb": "GENERAL PUBLIC COMMENT. Public comments that are not related to any of the items specifically listed on the agenda will be heard at approximately 9:00 am, for no more than one hour. At the discretion of the Chair, speakers may be given up to 2 minutes. Due to the transition to a virtual meeting platform, the Coastal Commission at this time will not allow for the ceding of time from one speaker to another speaker. Note: You may address the Commission on a specific topic one time only each month. Please submit a request to speak by 5:00 pm the day before the hearing to assist with meeting management sign up. We will stop taking speaker requests by 8:30 am on each day of the meeting. Please see the Coastal Commission\u2019s Virtual Hearing Procedures memo for submitting a request to speak. ",
        "subitem_number": "",
        "subitem_title": "",
        "subitem_blurb": "",
        "subitem_status": ""
    },
    {
        "date": "September 9, 2020",
        "district": "Statewide",
        "item_number": 5,
        "item_title": "Chair's Report",
        "item_blurb": "",
        "subitem_number": "",
        "subitem_title": "",
        "subitem_blurb": "",
        "subitem_status": ""
    },
    {
        "date": "September 9, 2020",
        "district": "Statewide",
        "item_number": 6,
        "item_title": "Executive Director's Report",
        "item_blurb": "",
        "subitem_number": "a",
        "subitem_title": "Executive Director's Report",
        "subitem_blurb": "",
        "subitem_status": ""
    },
    {
        "date": "September 9, 2020",
        "district": "Statewide",
        "item_number": 6,
        "item_title": "Executive Director's Report",
        "item_blurb": "",
        "subitem_number": "b",
        "subitem_title": "Commission Correspondence",
        "subitem_blurb": "Consideration and potential action on Commission correspondence.",
        "subitem_status": ""
    },
    {
        "date": "September 9, 2020",
        "district": "Statewide",
        "item_number": 6,
        "item_title": "Executive Director's Report",
        "item_blurb": "",
        "subitem_number": "c",
        "subitem_title": "Legislative Report",
        "subitem_blurb": "Status report and possible action on pending legislation. (JA/SC-SF)",
        "subitem_status": ""
    },
    {
        "date": "September 9, 2020",
        "district": "South Coast District (Orange County)",
        "item_number": 7,
        "item_title": "Administrative Calendar",
        "item_blurb": "",
        "subitem_number": "a",
        "subitem_title": "Application No. 5-19-0979 (San Jacinto LLC, Newport Beach) ",
        "subitem_blurb": "Application of San Jacinto LLC to remove \u201cU\u201d shaped boat dock float, gangway, pier, and pier platform and replace with new \u201cL\u201d shaped boat dock float, gangway, pier, and pier platform, at 626 Via Lido Nord, Newport Beach, Orange County. (MV-LB)",
        "subitem_status": "CONCURRED"
    },
    {
        "date": "September 9, 2020",
        "district": "South Coast District (Orange County)",
        "item_number": 7,
        "item_title": "Administrative Calendar",
        "item_blurb": "",
        "subitem_number": "b",
        "subitem_title": "Application No. 5-20-0184 (Horowitz, Newport Beach) ",
        "subitem_blurb": "Application of Ron Horowitz to remove 483.25 sq.ft. floating dock, 60 sq.ft. gangway, and three 12-in. pipe guide piles and construct 440 sq.ft. floating dock, 60 sq.ft. gangway, and two 12-pipe guide piles, at 618 Harbor Island Dr., Newport Beach, Orange County. (FSY-LB)",
        "subitem_status": "CONCURRED"
    },
    {
        "date": "September 9, 2020",
        "district": "South Coast District (Orange County)",
        "item_number": 8,
        "item_title": "Consent Calendar",
        "item_blurb": "",
        "subitem_number": "a",
        "subitem_title": "Application\u202fNo.\u202f5-19-0218 \u202f(Beach House LLC, Seal Beach)",
        "subitem_blurb": "Application of Beach House LLC to renovate 868 sq.ft. restaurant with 1,897 sq.ft. outdoor patio area and 522 sq.ft. covered patio, resulting in 15\u20192\u201d restaurant with parapet walls and 22\u20196\u201dtall tower, at 15 1st St., Seal Beach, Orange County. (AY-LB)",
        "subitem_status": "Postponed"
    },
    {
        "date": "September 9, 2020",
        "district": "South Coast District (Orange County)",
        "item_number": 8,
        "item_title": "Consent Calendar",
        "item_blurb": "",
        "subitem_number": "b",
        "subitem_title": "Application No. 5-19-1460 (Cooper, Seal Beach) ",
        "subitem_blurb": "Application of Adam Cooper to demolish 1,368 sq.ft., 2-story single-family home with attached 400 sq.ft., 2-car garage and construct 5,000 sq.ft. single-family home with attached 484 sq.ft. 2- car garage on beach front lot, at 540 Ocean Ave., Seal Beach, Orange County. (FSY-LB)",
        "subitem_status": "APPROVED WITH CONDITIONS"
    },
    {
        "date": "September 9, 2020",
        "district": "South Coast District (Orange County)",
        "item_number": 8,
        "item_title": "Consent Calendar",
        "item_blurb": "",
        "subitem_number": "c",
        "subitem_title": "Application No.\u202f 5-20-0095 (CD Asset Company, LLC, Laguna Beach) ",
        "subitem_blurb": "Application of CD Asset Company, LLC to remodel 2,932 sq.ft. single-family home on bluff-top lot, new upper level deck addition, new planters, and replace existing driveway at landward side of residence, at 12 S. La Senda Dr., Laguna Beach, Orange County. (AS-LB)",
        "subitem_status": "APPROVED WITH CONDITIONS"
    },
    {
        "date": "September 9, 2020",
        "district": "South Coast District (Orange County)",
        "item_number": 9,
        "item_title": "Consent Calendar (removed from Regular Calendar)",
        "item_blurb": "",
        "subitem_number": "",
        "subitem_title": "",
        "subitem_blurb": "",
        "subitem_status": ""
    },
    {
        "date": "September 9, 2020",
        "district": "South Coast District (Orange County)",
        "item_number": 10,
        "item_title": "Deputy Director's Report",
        "item_blurb": "Report by Deputy Director on permit waivers, emergency permits, immaterial amendments & extensions, and on comments from the public relating to the Deputy Director's report. For specific information contact the Commission's Long Beach office at (562) 590-5071.",
        "subitem_number": "",
        "subitem_title": "",
        "subitem_blurb": "",
        "subitem_status": ""
    },
    {
        "date": "September 9, 2020",
        "district": "South Coast District (Orange County)",
        "item_number": 11,
        "item_title": "Local Coastal Programs (LCPs)",
        "item_blurb": "",
        "subitem_number": "a",
        "subitem_title": "City of Newport Beach LCP Amendment No. \u202f(LCP-5-NPB-19-0016-1) (Parking Management Overlay District).",
        "subitem_blurb": "Public hearing and action on the request by the City of Newport Beach to amend the certified LCP Implementation Plan to create a new Parking Management Overlay District (PM Overlay) category and implementing procedures in the IP and to establish the first Parking Management District, PM-1 for the Balboa Village area of the City.\u202f(LR-LB)",
        "subitem_status": "Deny IP Amendment as Submitted/Approve IP Amendment with Suggested Mods"
    },
    {
        "date": "September 9, 2020",
        "district": "South Coast District (Orange County)",
        "item_number": 11,
        "item_title": "Local Coastal Programs (LCPs)",
        "item_blurb": "",
        "subitem_number": "b",
        "subitem_title": "City of Laguna Beach LCP Amendment No. LCP-5-LGB-20-0004-3",
        "subitem_blurb": "Concurrence with the Executive Director\u2019s determination that the action by the City of Laguna Beach accepting certification of LCP Amendment No. LCP-5-LGB-20-0004-3 with suggested modifications to correct or clarify ambiguities within the existing language of the implementation plan, more clearly identify what constitutes development requiring a CDP, and provide for a de minimis waiver and administrative review process, is legally adequate. (MA-LB) ",
        "subitem_status": "CONCURRED moved to consent"
    },
    {
        "date": "September 9, 2020",
        "district": "South Coast District (Orange County)",
        "item_number": 12,
        "item_title": "New Appeals",
        "item_blurb": "",
        "subitem_number": "a",
        "subitem_title": "Appeal No. A-5-LGB-20-0017 (Lions Pride Exempt Trust, Laguna Beach) ",
        "subitem_blurb": "Appeal by Mark and Sharon Fudge of City of Laguna Beach granting permit with conditions to Lions Pride Exempt Trust for conversion of existing detached guest house with storage to 1,164 sq. feet accessory dwelling unit in R-l (Residential Low Density) zone on oceanfront property that includes conversion of upper level 476 sq.ft. storage area for living space, at 31941 Coast Highway, Laguna Beach, Orange County. (MV-LB)",
        "subitem_status": "SUBSTANTIAL ISSUE FOUND, de Novo Hearing CONTINUED"
    },
    {
        "date": "September 9, 2020",
        "district": "South Coast District (Orange County)",
        "item_number": 13,
        "item_title": "Coastal Permit Applications",
        "item_blurb": "",
        "subitem_number": "a",
        "subitem_title": "Appeal No. A-5-LGB-18-0014 (Harle & Olvera, Laguna Beach) ",
        "subitem_blurb": "Appeal by Mark and Sharon Fudge of City of Laguna Beach granting permit with conditions to Peter Harle and Lori Olvera to remove damaged retaining wall; repair existing patio (replace flagstone flooring in kind, no patio expansion); and construct 36-in. tall PVC perimeter fence on patio, at 31101 Coast Highway, Laguna Beach, Orange County. (AS-LB)",
        "subitem_status": "Postponed"
    },
    {
        "date": "September 9, 2020",
        "district": "South Coast District (Orange County)",
        "item_number": 13,
        "item_title": "Coastal Permit Applications",
        "item_blurb": "",
        "subitem_number": "b",
        "subitem_title": "Application No. 5-18-0982 (Bolsa Chica Conservancy, Huntington Beach) ",
        "subitem_blurb": "Application of Bolsa Chica Conservancy to replace temporary Interpretive Center consisting of removal of 1,440 sq.ft. modular building, various storage outbuildings, and portable toilets and install new 1,440 sq.ft. temporary Interpretive Center, pre-fabricated modular building and new 1,200 sq.ft., pre-fabricated, modular building connected to existing building, at 3842 Warner Ave., Huntington Beach, Orange County. (MV-LB)",
        "subitem_status": "Moved to Consent Calendar, APPROVED WITH CONDITIONS"
    },
    {
        "date": "September 9, 2020",
        "district": "South Coast District (Orange County)",
        "item_number": 13,
        "item_title": "Coastal Permit Applications",
        "item_blurb": "",
        "subitem_number": "c",
        "subitem_title": "Application No. 5-19-0971 (Dana Point Harbor Partners, LLC, Dana Point) ",
        "subitem_blurb": "Application of Dana Point Harbor Partners, LLC to: (1) replace 2,409 recreational boat slip marina with 2,254 recreational boat slip marina; (2) replace 11 yacht club slips with 13 yacht club slips in the Dana Point Yacht Club in Inner Basin; (3) replace 16 sportfishing charter slips and 1 dock-and-dine guest dock adjacent to Catalina ferry; (4) relocate and reconfigure fuel dock and emergency dock; (5) relocate bait dock, replace 16 commercial fishing slips, and install new drive-in boat wash in Outer Basin; (6) relocate and expand transient guest docks to Outer Basin; (7) replace 11 existing boater service buildings with 10 boater service buildings; (8) repair 9,964 linear feet of seawalls/revetment; (9) replace 1,644 designated boater parking spaces with 1,410 spaces; (10) and relocate and expand  parkscape and public access areas closer to the water, at 24650 Dana Point Harbor Dr., Dana Point, Orange County. (CP-LB)",
        "subitem_status": "APPROVED WITH CONDITIONS"
    },
    {
        "date": "September 9, 2020",
        "district": "South Coast District (Orange County)",
        "item_number": 13,
        "item_title": "Coastal Permit Applications",
        "item_blurb": "",
        "subitem_number": "d",
        "subitem_title": "Application No. 5-19-1036 (Blue Lagoon Community Association, Laguna Beach) ",
        "subitem_blurb": "Application of Blue Lagoon Community Association for slope remediation on coastal bluff consisting of placement of shotcrete wall, brow ditches, and drainage pipe; replace lawn area with decomposed granite; and replant with low water use and native plants, at 30781 South Coast Highway, Laguna Beach, Orange County. (MV-LB)",
        "subitem_status": "APPROVED WITH CONDITIONS"
    },
    {
        "date": "September 9, 2020",
        "district": "South Coast District (Orange County)",
        "item_number": 13,
        "item_title": "Coastal Permit Applications",
        "item_blurb": "",
        "subitem_number": "e",
        "subitem_title": "Application No. 5-19-1155 (Wojtaszek, Laguna Beach) ",
        "subitem_blurb": "Application of David and Jenny Wojtaszek to demolish 3,763 sq.ft. single-family home and construct new 5,946 sq.ft., 14-ft. high above natural grade, 2 level single-family home with attached 527 sq.ft., 3 car garage; along with 1,380 cu.yds. of cut and 260 cu.yds. of fill for lower level and swimming pool, at 2580 Riviera Dr., Laguna Beach, Orange County. (MV-LB)",
        "subitem_status": "Moved to Consent Calendar, APPROVED WITH CONDITIONS"
    },
    {
        "date": "September 9, 2020",
        "district": "South Coast District (Orange County)",
        "item_number": 13,
        "item_title": "Coastal Permit Applications",
        "item_blurb": "",
        "subitem_number": "f",
        "subitem_title": "Application No. 5-19-1239 (City of San Clemente Department of Public Works Parking Meter Program) ",
        "subitem_blurb": "Application of City of San Clemente Dept. of Public Works to remove City parking meters at two beach parking areas, including Camino Capistrano (14 double head meters, 1 single head), and Avenida Calafia (11 double head meters, 1 single head), and limit use of parking in these 2 locations to maximum duration of 4 hours; and change hours of operation for all other existing metered parking areas (North Beach, Linda Lane, Pier Bowl, T-Street/Paseo De Cristobal) to 9 am. to 10 pm. No change to the $1.50/hour fee is proposed, at San Clemente, Orange County. (MR-LB)",
        "subitem_status": "APPROVED WITH CONDITIONS"
    },
    {
        "date": "September 9, 2020",
        "district": "South Coast District (Orange County)",
        "item_number": 13,
        "item_title": "Coastal Permit Applications",
        "item_blurb": "",
        "subitem_number": "g",
        "subitem_title": "Application No. 5-19-1466 (City of Newport Beach Dock Improvements) ",
        "subitem_blurb": "Application of City of Newport Beach to repair existing bulkhead consisting of removal and replacement of cap and installation of new tiebacks and also removal of gangway and installation of new gangway platform and ADA compliant gangway and expansion of dock float, at 215 15th St., Newport Beach, Orange County. (FSY-LB)",
        "subitem_status": "Approved with Staff Modification"
    },
    {
        "date": "September 9, 2020",
        "district": "South Coast District (Orange County)",
        "item_number": 14,
        "item_title": "Revised Findings",
        "item_blurb": "",
        "subitem_number": "a",
        "subitem_title": "Appeal No. A-5-LGB-20-0001 (City of Laguna Beach Parking Fee Program) ",
        "subitem_blurb": "Consideration of findings in support for Commission\u2019s July 8, 2020 decision to deny the De Novo permit request by the City of Laguna Beach, for approval to establish a multi-year, multi-phase parking rate structure for summer and non-summer months for all public meters and lots/structures located citywide Laguna Beach, Orange County. (VL-LB)",
        "subitem_status": "APPROVED"
    },
    {
        "date": "September 9, 2020",
        "district": "Statewide",
        "item_number": false,
        "item_title": "Closed Session",
        "item_blurb": "At a convenient time during the meeting, the Commission (CCC) will have a closed session to discuss items of pending litigation, including:",
        "subitem_number": "",
        "subitem_title": "",
        "subitem_blurb": "",
        "subitem_status": ""
    },
    {
        "date": "September 9, 2020",
        "district": "Statewide",
        "item_number": 15,
        "item_title": "APPROVAL OF MINUTES (August 2020)",
        "item_blurb": "",
        "subitem_number": "",
        "subitem_title": "",
        "subitem_blurb": "",
        "subitem_status": ""
    },
    {
        "date": "September 9, 2020",
        "district": "Statewide",
        "item_number": 16,
        "item_title": "COMMISSIONERS\u2019 REPORTS",
        "item_blurb": "",
        "subitem_number": "",
        "subitem_title": "",
        "subitem_blurb": "",
        "subitem_status": ""
    },
    {
        "date": "September 9, 2020",
        "district": "Statewide",
        "item_number": 17,
        "item_title": "COMMISSION SUB-COMMITTEE REPORTS",
        "item_blurb": "",
        "subitem_number": "",
        "subitem_title": "",
        "subitem_blurb": "",
        "subitem_status": ""
    },
    {
        "date": "September 9, 2020",
        "district": "Statewide",
        "item_number": 18,
        "item_title": "CONSERVANCY REPORT",
        "item_blurb": "",
        "subitem_number": "",
        "subitem_title": "",
        "subitem_blurb": "",
        "subitem_status": ""
    },
    {
        "date": "September 9, 2020",
        "district": "Statewide",
        "item_number": 19,
        "item_title": "SANTA MONICA MOUNTAINS CONSERVANCY REPORT",
        "item_blurb": "",
        "subitem_number": "",
        "subitem_title": "",
        "subitem_blurb": "",
        "subitem_status": ""
    },
    {
        "date": "September 9, 2020",
        "district": "Statewide",
        "item_number": 20,
        "item_title": "SANTA MONICA BAY RESTORATION REPORT",
        "item_blurb": "",
        "subitem_number": "",
        "subitem_title": "",
        "subitem_blurb": "",
        "subitem_status": ""
    },
    {
        "date": "September 9, 2020",
        "district": "Statewide",
        "item_number": 21,
        "item_title": "DEPUTY ATTORNEY GENERAL\u2019S REPORT",
        "item_blurb": "",
        "subitem_number": "",
        "subitem_title": "",
        "subitem_blurb": "",
        "subitem_status": ""
    },
    {
        "date": "September 10, 2020",
        "district": "Statewide",
        "item_number": 1,
        "item_title": "CALL TO ORDER and ROLL CALL.",
        "item_blurb": "",
        "subitem_number": "",
        "subitem_title": "",
        "subitem_blurb": "",
        "subitem_status": ""
    },
    {
        "date": "September 10, 2020",
        "district": "Statewide",
        "item_number": 2,
        "item_title": "VIRTUAL MEETING PROCEDURES",
        "item_blurb": "",
        "subitem_number": "",
        "subitem_title": "",
        "subitem_blurb": "",
        "subitem_status": ""
    },
    {
        "date": "September 10, 2020",
        "district": "Statewide",
        "item_number": 3,
        "item_title": "Agenda Changes",
        "item_blurb": "",
        "subitem_number": "",
        "subitem_title": "",
        "subitem_blurb": "",
        "subitem_status": ""
    },
    {
        "date": "September 10, 2020",
        "district": "Statewide",
        "item_number": 4,
        "item_title": "General Public Comment",
        "item_blurb": "GENERAL PUBLIC COMMENT. Public comments that are not related to any of the items specifically listed on the agenda will be heard at approximately 9:00 am, for no more than one hour. At the discretion of the Chair, speakers may be given up to 2 minutes. Due to the transition to a virtual meeting platform, the Coastal Commission at this time will not allow for the ceding of time from one speaker to another speaker. Note: You may address the Commission on a specific topic one time only each month. Please submit a request to speak by 5:00 pm the day before the hearing to assist with meeting management sign up. We will stop taking speaker requests by 8:30 am on each day of the meeting. Please see the Coastal Commission\u2019s Virtual Hearing Procedures memo for submitting a request to speak.",
        "subitem_number": "",
        "subitem_title": "",
        "subitem_blurb": "",
        "subitem_status": ""
    },
    {
        "date": "September 10, 2020",
        "district": "Statewide",
        "item_number": 5,
        "item_title": "Consent Calendar",
        "item_blurb": "",
        "subitem_number": "a",
        "subitem_title": "Application No. 6-19-1013 (Caulfield et al., Oceanside) ",
        "subitem_blurb": "Application of Matt & Pat Caulfield et al., to authorize maintenance consisting of relocating existing rock onto existing approx. 660 ft. long, 20 ft. wide (approx. 13,200 sq.ft.) rock revetment fronting 13 homes and one vacant lot, between 1931-2031 South Pacific St., Oceanside, San Diego County. (TR-SD)",
        "subitem_status": "APPROVED WITH CONDITIONS"
    },
    {
        "date": "September 10, 2020",
        "district": "Statewide",
        "item_number": 6,
        "item_title": "Consent Calendar (removed from Regular Calendar)",
        "item_blurb": "",
        "subitem_number": "",
        "subitem_title": "",
        "subitem_blurb": "",
        "subitem_status": ""
    },
    {
        "date": "September 10, 2020",
        "district": "San Diego Coast District",
        "item_number": 7,
        "item_title": "Deputy Director's Report",
        "item_blurb": "Report by Deputy Director on permit waivers, emergency permits, immaterial amendments & extensions, and on comments from the public relating to the Deputy Director's report. For specific information contact the Commission's San Diego office at (619) 767-2370.",
        "subitem_number": "",
        "subitem_title": "",
        "subitem_blurb": "",
        "subitem_status": ""
    },
    {
        "date": "September 10, 2020",
        "district": "San Diego Coast District",
        "item_number": 8,
        "item_title": "Local Coastal Programs (LCPs)",
        "item_blurb": "",
        "subitem_number": "a",
        "subitem_title": "City of Oceanside LCP Amendment No. LCP-6-OCN-20-0048-1 (Article 41 Revisions) Time Extension. ",
        "subitem_blurb": "Public hearing and action to extend the 60-day time limit for Commission action for up to one year on request by the City of Oceanside to amend its certified Implementation Plan to revise certain regulations regarding use permits and variances. (TR-SD)",
        "subitem_status": "Approved moved to consent"
    },
    {
        "date": "September 10, 2020",
        "district": "San Diego Coast District",
        "item_number": 8,
        "item_title": "Local Coastal Programs (LCPs)",
        "item_blurb": "",
        "subitem_number": "b",
        "subitem_title": "City of San Diego LCP Amendment No. LCP-6-SAN-19-0141-2 (Civic San Diego Dissolution) Certification Review",
        "subitem_blurb": "Concurrence with Executive Director\u2019s determination that action by the City of San Diego accepting the Commission\u2019s certification with suggested modifications is legally adequate. (ML-SD)",
        "subitem_status": "CONCURRED moved to consent"
    },
    {
        "date": "September 10, 2020",
        "district": "San Diego Coast District",
        "item_number": 8,
        "item_title": "Local Coastal Programs (LCPs)",
        "item_blurb": "",
        "subitem_number": "c",
        "subitem_title": "City of San Diego LCP Amendment No. LCP-6-SAN-20-0045-2 (Inclusionary Housing Regulations) Time Extension",
        "subitem_blurb": "Public hearing and action to extend the 60-day time limit for Commission action for up to one year on request by the City of San Diego to amend its certified Implementation Plan regarding inclusionary housing regulations. (AL-SD)",
        "subitem_status": "Approved moved to consent"
    },
    {
        "date": "September 10, 2020",
        "district": "San Diego Coast District",
        "item_number": 9,
        "item_title": "New Appeals",
        "item_blurb": "",
        "subitem_number": "a",
        "subitem_title": "Appeal No. A-6-NOC-02-087 (Newland Group, Inc., Tierra Alta, San Diego) ",
        "subitem_blurb": "Appeal by Commissioners Wan and McCoy from decision of City of San Diego granting permit with conditions to Newland Group, Inc. for subdivision of 4.44-acre site into 10 lots and construction of 11 single-family dwelling units on site located at northerly terminus of Caminito Rodar, Mira Mesa, North City, San Diego, San Diego County. (TR-SD)",
        "subitem_status": "NO SUBSTANTIAL ISSUE FOUND"
    },
    {
        "date": "September 10, 2020",
        "district": "San Diego Coast District",
        "item_number": 9,
        "item_title": "New Appeals",
        "item_blurb": "",
        "subitem_number": "b",
        "subitem_title": "Appeal No. A-6-LJS-19-0198 (San Diego Children\u2019s Pool Retaining Wall, San Diego) ",
        "subitem_blurb": "Appeal by La Jolla Community Planning Association & Ken Hunrichs from decision of City of San Diego that after-the-fact approval of 30-in. tall retaining wall substantially conforms to City\u2019s approval for construction of new lifeguard tower at Children\u2019s Pool Beach, La Jolla, San Diego, San Diego County. (ML-SD)",
        "subitem_status": "NO SUBSTANTIAL ISSUE FOUND"
    },
    {
        "date": "September 10, 2020",
        "district": "San Diego Coast District",
        "item_number": 9,
        "item_title": "New Appeals",
        "item_blurb": "",
        "subitem_number": "c",
        "subitem_title": "Appeal No. A-6-SAN-20-0029 (San Diego Municipal Waterways Maintenance Plan) ",
        "subitem_blurb": "Appeal by Commissioners Brownsey and Hart from decision of City of San Diego granting programmatic permit with conditions to implement Municipal Waterways Maintenance Program, a city-wide program governing on-going repair, maintenance and mitigation for city storm water infrastructure improvements, San Diego, San Diego County. (AL-SD)",
        "subitem_status": "SUBSTANTIAL ISSUE FOUND, de Novo Hearing CONTINUED"
    },
    {
        "date": "September 10, 2020",
        "district": "San Diego Coast District",
        "item_number": 10,
        "item_title": "Coastal Permit Applications",
        "item_blurb": "",
        "subitem_number": "a",
        "subitem_title": "Application No. 6-18-0745 (Wulbert, Encinitas) ",
        "subitem_blurb": "Application of Daniel Wulbert to retain 60 ft.-long slope stabilization system consisting of porous plastic mat below steel mesh secured by approx. 18 ft.-deep soil nails placed under emergency authorization, extend stabilization system by 55 feet, install ten 40 ft.-long hydraugers, remove vegetation, and conduct revegetation on bank of San Elijo Lagoon, at 2550 and 2560 San Elijo Ave., Encinitas, San Diego County. (ML-SD)",
        "subitem_status": "Moved to Consent Calendar, APPROVED WITH CONDITIONS"
    },
    {
        "date": "September 10, 2020",
        "district": "San Diego Coast District",
        "item_number": 10,
        "item_title": "Coastal Permit Applications",
        "item_blurb": "",
        "subitem_number": "b",
        "subitem_title": "Application No. 6-19-1291 (DeSimone, Schrager, & Oene, Solana Beach) ",
        "subitem_blurb": "Application of DeSimone, et al. to construct 50 ft. long, 35 ft. high seawall including geogrid structure with landscaping at public beach and bluff located between 249 and 241 Pacific Ave., Solana Beach, San Diego County. (DD-SD)",
        "subitem_status": "Denied"
    },
    {
        "date": "September 10, 2020",
        "district": "San Diego Coast District",
        "item_number": 10,
        "item_title": "Coastal Permit Applications",
        "item_blurb": "",
        "subitem_number": "c",
        "subitem_title": "Application No. 6-20-0231 (California Department of Transportation Cable Fencing) ",
        "subitem_blurb": "Application of Caltrans to install 32,850 linear ft. of post and wire cable fencing with vegetation control; replace 1,700 linear feet of existing guardrails; remove vegetation; and upgrade existing dikes, drainage system and end treatments, at four locations on shoulder of Interstate 5 highway in Camp Pendleton Marine Corps Base, north of Oceanside and south of San Onofre Creek bridge, San Diego County. (KL-SD)",
        "subitem_status": "Moved to Consent Calendar, APPROVED WITH CONDITIONS"
    },
    {
        "date": "September 10, 2020",
        "district": "San Diego Coast District",
        "item_number": 11,
        "item_title": "Permit Amendments",
        "item_blurb": "",
        "subitem_number": "a",
        "subitem_title": "Permit No. 6-90-271-A1 (Jorgensen and Urquidi, Encinitas) ",
        "subitem_blurb": "Request by Bret Jorgensen and Susan Urquidi to amend permit for construction of 2-story, 4,800 sq.ft. single-family home on vacant blufftop lot to add 270 sq.ft. cantilevered second floor addition and new interior elevator on 3,950 sq.ft. lot, at 1316 Neptune Ave., Encinitas, San Diego County. (CH-SD)",
        "subitem_status": "APPROVED moved to consent"
    },
    {
        "date": "September 10, 2020",
        "district": "South Central Coast District",
        "item_number": 12,
        "item_title": "Deputy Director's Report",
        "item_blurb": "Report by Deputy Director on permit waivers, emergency permits, immaterial amendments & extensions, and on comments from the public relating to the Deputy Director's report. For specific information contact the Commission's Ventura office at (805) 585-1800.",
        "subitem_number": "",
        "subitem_title": "",
        "subitem_blurb": "",
        "subitem_status": ""
    },
    {
        "date": "September 10, 2020",
        "district": "South Central Coast District",
        "item_number": 13,
        "item_title": "Local Coastal Programs (LCPs)",
        "item_blurb": "",
        "subitem_number": "a",
        "subitem_title": "City of Malibu LCP Amendment No. LCP-4-MAL-19-0164-3 (Prohibit the Use of Pesticides) Time Extension",
        "subitem_blurb": "Public hearing and action to extend the time limit for action for one year on City of Malibu\u2019s request to amend the Land Use Plan (LUP) portion of its certified LCP with regard to a citywide prohibition on pesticides. (DV-V)",
        "subitem_status": "Approved moved to consent"
    },
    {
        "date": "September 10, 2020",
        "district": "South Central Coast District",
        "item_number": 13,
        "item_title": "Local Coastal Programs (LCPs)",
        "item_blurb": "",
        "subitem_number": "b",
        "subitem_title": "County of Santa Barbara LCP Amendment No. LCP-4-STB-20-0028-1 (Policies and Standards for Coastal Hazards and Planning for Sea Level Rise). Time Extension",
        "subitem_blurb": "Public hearing and action to extend the time limit for action for one year on County of Santa Barbara\u2019s request to amend the Land Use Plan and the Implementation Plan of its certified LCP to add policies and development standards regarding coastal hazards and planning for sea level rise. (MK-V)",
        "subitem_status": "Approved moved to consent"
    },
    {
        "date": "September 10, 2020",
        "district": "South Central Coast District",
        "item_number": 14,
        "item_title": "Coastal Permit Applications",
        "item_blurb": "",
        "subitem_number": "a",
        "subitem_title": "Application No. 4-18-1261 (City of Goleta Fire Station, Santa Barbara Co.) ",
        "subitem_blurb": "Application of City of Goleta to construct 11,600 sq.ft. one-story fire station with 3 drive-through bays and associated apparatus, 1,250 gallon above-ground fuel tank, employee and public parking spaces, and drought tolerant landscaping on vacant parcel at 7952 Hollister Ave. in Goleta, Santa Barbara County. (MK-V)",
        "subitem_status": "APPROVED WITH CONDITIONS"
    },
    {
        "date": "September 10, 2020",
        "district": "South Coast District (Los Angeles County)",
        "item_number": 15,
        "item_title": "Deputy Director's Report For Los Angeles County",
        "item_blurb": "Report by Deputy Director on permit waivers, emergency permits, immaterial amendments & extensions, and on comments from the public relating to the Deputy Director's report. For specific information contact the Commission's Long Beach office at (562) 590-5071.",
        "subitem_number": "",
        "subitem_title": "",
        "subitem_blurb": "",
        "subitem_status": ""
    },
    {
        "date": "September 10, 2020",
        "district": "South Coast District (Los Angeles County)",
        "item_number": 16,
        "item_title": "Local Coastal Programs (LCPs)",
        "item_blurb": "",
        "subitem_number": "a",
        "subitem_title": "City of Long Beach LCP Amendment No. 3-18C (LCP-5-LOB-18-0100-3-Part C). ",
        "subitem_blurb": "Concurrence with the Executive Director\u2019s determination that action by the City of Long Beach accepting the Commission\u2019s certification with suggested modifications is legally adequate. (DZ-LB)",
        "subitem_status": "CONCURRED moved to consent"
    },
    {
        "date": "September 10, 2020",
        "district": "South Coast District (Los Angeles County)",
        "item_number": 16,
        "item_title": "Local Coastal Programs (LCPs)",
        "item_blurb": "",
        "subitem_number": "b",
        "subitem_title": "City of Long Beach LCP Amendment LCP-5-LOB-20-0042-2 - Time Extensions for Permits",
        "subitem_blurb": "Concurrence with the Executive Director\u2019s determination that the request by the City of Long Beach to amend Section 21.21.406 of the Implementation Plan (IP) portion of the certified LCP to extend expiration deadlines for local permits is minor. (DZ-LB)",
        "subitem_status": "CONCURRED moved to consent"
    },
    {
        "date": "September 10, 2020",
        "district": "South Coast District (Los Angeles County)",
        "item_number": false,
        "item_title": "Items Th17a and Th18a below will share a combined staff report and hearing",
        "item_blurb": "",
        "subitem_number": "",
        "subitem_title": "",
        "subitem_blurb": "",
        "subitem_status": ""
    },
    {
        "date": "September 10, 2020",
        "district": "South Coast District (Los Angeles County)",
        "item_number": 17,
        "item_title": "Permit Amendments",
        "item_blurb": "",
        "subitem_number": "a",
        "subitem_title": "Permit Nos.\u202f A-5-VEN-17-0051-A1/5-17-0892-A1 (305 Ocean Front Walk Development, LLC, Venice, Los Angeles) ",
        "subitem_blurb": "Request by 305 Ocean Front Walk Development, LLC to amend permits to authorize parcel map for 3 condominium units previously approved as apartment units within previously approved 3-story, 10,430 sq.ft. mixed use development with 2,850 sq.ft. ground floor retail, 3 artist-in-residence units, 23 vehicle spaces, and 16 bicycle parking spaces at 305-309 Ocean Front Walk, Venice, Los Angeles, Los Angeles County. (AS-LB)",
        "subitem_status": "APPROVED WITH CONDITIONS"
    },
    {
        "date": "September 10, 2020",
        "district": "South Coast District (Los Angeles County)",
        "item_number": 18,
        "item_title": "New Appeals",
        "item_blurb": "",
        "subitem_number": "a",
        "subitem_title": "Appeal No. A-5-VEN-20-0023 (305 Ocean Front Walk Development, LLC, Venice, Los Angeles) ",
        "subitem_blurb": "Appeal by Margaret Molloy of City of Los Angeles action granting permit to 305 Ocean Front Walk Development, LLC with conditions for lot merger, tentative tract map, and construction of 3-story, 10,430 sq.ft. mixed use development with 2,850 sq.ft. ground floor retail, 3 residential condo units,  23 vehicle spaces, and 12 bicycle parking spaces, at 305-309 Ocean Front Walk, Venice, Los Angeles, Los Angeles County. (AS-LB)",
        "subitem_status": "SUBSTANTIAL ISSUE FOUND, Approved with conditions"
    },
    {
        "date": "September 10, 2020",
        "district": "South Coast District (Los Angeles County)",
        "item_number": 18,
        "item_title": "New Appeals",
        "item_blurb": "",
        "subitem_number": "b",
        "subitem_title": "Appeal No. A-5-VEN-17-0016 (Korchia, Venice, Los Angeles) ",
        "subitem_blurb": "Appeal by Robin Rudisill et al., of City of Los Angeles action granting permit with conditions to Fabienne Korchia for demolition of single\u2013story-family home and construction of 3,400 sq.ft., 24-ft. high, 2-story, single-family home with attached 370 sq.ft. 2-car garage, plus one additional on-site parking space, and roof deck with 34-ft. high roof access structure, at 2325 Wilson Ave., Venice, Los Angeles, Los Angeles County. (CS-LB)  (Note: The Commission\u2019s enforcement division has opened an investigation into potential Coastal Act violations associated with this item and site, as is explained further in the staff report.)",
        "subitem_status": "NO SUBSTANTIAL ISSUE FOUND"
    },
    {
        "date": "September 10, 2020",
        "district": "South Coast District (Los Angeles County)",
        "item_number": 19,
        "item_title": "Coastal Permit Applications",
        "item_blurb": "",
        "subitem_number": "a",
        "subitem_title": "Application No. 5-19-0243 (Bel Air Bay Club, Pacific Palisades, Los Angeles) ",
        "subitem_blurb": "Application of Bel Air Bay Club to construct temporary sand berm (approximately 430 ft. long and 13,140 sq. ft.) between the upcoast and downcoast groins using on-site sand to protect against wave uprush and inundation of Club facilities during extreme high tide and/or swell events; relocation of the Palapas and Playground; and payment of funds to the Boys and Girls Club of Venice's Fast and Fun sailing program, at 16800 Pacific Coast Highway, Pacific Palisades, Los Angeles, Los Angeles County. (DN-SF) ",
        "subitem_status": "Postponed"
    },
    {
        "date": "September 10, 2020",
        "district": "South Coast District (Los Angeles County)",
        "item_number": 19,
        "item_title": "Coastal Permit Applications",
        "item_blurb": "",
        "subitem_number": "b",
        "subitem_title": "Application No. 5-19-1167 (Harley GCS, LLC, Venice, Los Angeles) ",
        "subitem_blurb": "Application of Harley GCS, LLC to construct 33.8-ft. high, 3-story, 4,827 sq.ft. single-family home with partially subterranean basement, 530 sq.ft. accessory dwelling unit, and attached 2-car garage, on 3,545 sq.ft. vacant lot, at 3819 Via Dolce, Venice, Los Angeles, Los Angeles County. (CS-LB)",
        "subitem_status": "Moved to Consent Calendar, APPROVED WITH CONDITIONS"
    },
    {
        "date": "September 10, 2020",
        "district": "South Coast District (Los Angeles County)",
        "item_number": 19,
        "item_title": "Coastal Permit Applications",
        "item_blurb": "",
        "subitem_number": "c",
        "subitem_title": "Application No. 5-19-1244 (TSNH Investments, LLC, Hermosa Beach) ",
        "subitem_blurb": "Application of TSNH Investments, LLC to demolish 2- story, 2,443 sq.ft. duplex and construct 2-story (over partial basement), 3,850 sq.ft. single-family home with 450 sq.ft. junior accessory dwelling unit, attached 375 sq.ft., 2-car garage, and one guest parking space adjacent to garage, at 3411 The Strand, Hermosa Beach, Los Angeles County. (AS-LB)",
        "subitem_status": "APPROVED WITH CONDITIONS"
    },
    {
        "date": "September 10, 2020",
        "district": "South Coast District (Los Angeles County)",
        "item_number": 19,
        "item_title": "Coastal Permit Applications",
        "item_blurb": "",
        "subitem_number": "d",
        "subitem_title": "Application No. 5-20-0142 (316 24th St. Holdings, LLC, Hermosa Beach) ",
        "subitem_blurb": "Application of 316 24th St. Holdings, LLC to demolish two-unit residential structure consisting of 2,173 sq.ft. primary unit and 528 sq.ft. accessory unit and construct 25-ft. high, 3-story over basement, 4,118 sq.ft. single-family home with attached 531 sq.ft. accessory dwelling unit and attached 2-car garage, at 316 24th St., Hermosa Beach, Los Angeles County. (CS-LB)",
        "subitem_status": "APPROVED WITH CONDITIONS"
    },
    {
        "date": "September 10, 2020",
        "district": "South Coast District (Los Angeles County)",
        "item_number": 19,
        "item_title": "Coastal Permit Applications",
        "item_blurb": "",
        "subitem_number": "e",
        "subitem_title": "Application No. 5-20-0223 (Wang, Hermosa Beach) ",
        "subitem_blurb": "Application of Clifford Wang to demolish 2-story, 1,100 sq.ft. duplex and detached garage, and construct new 2-story (over basement), 30-ft. high, 3,550 sq.ft. single-family home with attached accessory dwelling unit, attached 2-car garage and one guest parking space in driveway, at 1820 Manhattan Ave., Hermosa Beach, Los Angeles County. (VL-LB) ",
        "subitem_status": "APPROVED WITH CONDITIONS"
    },
    {
        "date": "September 10, 2020",
        "district": "South Coast District (Los Angeles County)",
        "item_number": 19,
        "item_title": "Coastal Permit Applications",
        "item_blurb": "",
        "subitem_number": "f",
        "subitem_title": "Application 5-20-0237 (Munjal, Santa Monica) ",
        "subitem_blurb": "Application of Kapil Munjal to demolish 2-story, 4,111 sq.ft. single-family home with pool (after-the-fact) and construct 2-story, approx. 25-ft. high (above finished grade), 14,135 sq.ft. single-family home with basement, 3-car garage, and new pool, at 222 Marguerita Ave., Santa Monica, Los Angeles County. (JD-LB)",
        "subitem_status": "APPROVED WITH CONDITIONS"
    },
    {
        "date": "September 11, 2020",
        "district": "Statewide",
        "item_number": 1,
        "item_title": "CALL TO ORDER and ROLL CALL",
        "item_blurb": "",
        "subitem_number": "",
        "subitem_title": "",
        "subitem_blurb": "",
        "subitem_status": ""
    },
    {
        "date": "September 11, 2020",
        "district": "Statewide",
        "item_number": 2,
        "item_title": "VIRTUAL MEETING PROCEDURES",
        "item_blurb": "",
        "subitem_number": "",
        "subitem_title": "",
        "subitem_blurb": "",
        "subitem_status": ""
    },
    {
        "date": "September 11, 2020",
        "district": "Statewide",
        "item_number": 3,
        "item_title": "Agenda Changes",
        "item_blurb": "",
        "subitem_number": "",
        "subitem_title": "",
        "subitem_blurb": "",
        "subitem_status": ""
    },
    {
        "date": "September 11, 2020",
        "district": "Statewide",
        "item_number": 4,
        "item_title": "General Public Comment",
        "item_blurb": "GENERAL PUBLIC COMMENT. Public comments that are not related to any of the items specifically listed on the agenda will be heard at approximately 9:00 am, for no more than one hour. At the discretion of the Chair, speakers may be given up to 2 minutes. Due to the transition to a virtual meeting platform, the Coastal Commission at this time will not allow for the ceding of time from one speaker to another speaker. Note: You may address the Commission on a specific topic one time only each month. Please submit a request to speak by 5:00 pm the day before the hearing to assist with meeting management sign up. We will stop taking speaker requests by 8:30 am on each day of the meeting. Please see the Coastal Commission\u2019s Virtual Hearing Procedures memo for submitting a request to speak. ",
        "subitem_number": "",
        "subitem_title": "",
        "subitem_blurb": "",
        "subitem_status": ""
    },
    {
        "date": "September 11, 2020",
        "district": "Statewide",
        "item_number": 5,
        "item_title": "Consent Calendar",
        "item_blurb": "",
        "subitem_number": "",
        "subitem_title": "",
        "subitem_blurb": "",
        "subitem_status": ""
    },
    {
        "date": "September 11, 2020",
        "district": "Statewide",
        "item_number": 6,
        "item_title": "Consent Calendar (removed from Regular Calendar)",
        "item_blurb": "",
        "subitem_number": "",
        "subitem_title": "",
        "subitem_blurb": "",
        "subitem_status": ""
    },
    {
        "date": "September 11, 2020",
        "district": "North Central Coast District",
        "item_number": 7,
        "item_title": "Deputy Director's Report",
        "item_blurb": "Report by Deputy Director on permit waivers, emergency permits, immaterial amendments & extensions, and on comments from the public relating to the Deputy Director's report.  For specific information contact the Commission\u2019s San Francisco office at (415) 904-5260.",
        "subitem_number": "",
        "subitem_title": "",
        "subitem_blurb": "",
        "subitem_status": ""
    },
    {
        "date": "September 11, 2020",
        "district": "Central Coast District",
        "item_number": 8,
        "item_title": "Deputy Director's Report",
        "item_blurb": "Report by Deputy Director on permit waivers, emergency permits, immaterial amendments & extensions, and on comments from the public relating to the Deputy Director's report.  For specific information contact the Commission\u2019s Santa Cruz office at (831) 427-4863.",
        "subitem_number": "",
        "subitem_title": "",
        "subitem_blurb": "",
        "subitem_status": ""
    },
    {
        "date": "September 11, 2020",
        "district": "Central Coast District",
        "item_number": 9,
        "item_title": "Local Coastal Programs (LCPs)",
        "item_blurb": "",
        "subitem_number": "a",
        "subitem_title": "City of Capitola LCP Amendment No. LCP-3-CAP-20-0029-1-Part A (ADUs). ",
        "subitem_blurb": "Concurrence with the Executive Director\u2019s determination that the request by the City of Capitola to modify the LCP\u2019s accessory dwelling unit provisions, consistent with recent changes to state housing law, is de minimis. (RG-SC)",
        "subitem_status": "CONCURRED Moved to consent"
    },
    {
        "date": "September 11, 2020",
        "district": "Central Coast District",
        "item_number": 9,
        "item_title": "Local Coastal Programs (LCPs)",
        "item_blurb": "",
        "subitem_number": "b",
        "subitem_title": "City of Capitola LCP Amendment No. LCP-3-CAP-20-0030-1-Part B (Signs). ",
        "subitem_blurb": "Concurrence with the Executive Director\u2019s determination that the request by the City of Capitola to modify the LCP\u2019s sign ordinance is minor. (RG-SC)",
        "subitem_status": "CONCURRED Moved to consent"
    },
    {
        "date": "September 11, 2020",
        "district": "Central Coast District",
        "item_number": 9,
        "item_title": "Local Coastal Programs (LCPs)",
        "item_blurb": "",
        "subitem_number": "c",
        "subitem_title": "City of Pismo Beach LCP Amendment No. LCP-3-PSB-20-0037-1 (Residential Very-High-Density Overlay and 855 4th Street Re-Designation/Re-Zoning). ",
        "subitem_blurb": "Public hearing and action on application by City of Pismo Beach to amend the LCP to: 1) add a new Residential Very-High-Density Overlay District (RVHD); and 2) re-designate a 1.2-acre parcel at 855 4th Street from General Commercial (GC) to Resort Residential \u2013 High Density (RR-H) and rezone the parcel from Retail Commercial (C-1) to High Density Residential (R-3) with the RVHD Overlay. (KB-SC)",
        "subitem_status": "Moved to consent Approved LUP & IP Amendment with Suggested Modifications"
    },
    {
        "date": "September 11, 2020",
        "district": "Central Coast District",
        "item_number": 9,
        "item_title": "Local Coastal Programs (LCPs)",
        "item_blurb": "",
        "subitem_number": "d",
        "subitem_title": "City of Grover Beach LCP Amendment No. LCP-3-GRB-20-0046-1 (ADUs). ",
        "subitem_blurb": "Concurrence with the Executive Director\u2019s determination that the request by City of Grover Beach to modify the LCP\u2019s accessory dwelling unit provisions, consistent with recent changes to state housing law, is de minimis. (EW-SC)",
        "subitem_status": "CONCURRED moved to consent"
    },
    {
        "date": "September 11, 2020",
        "district": "Central Coast District",
        "item_number": 10,
        "item_title": "NOTICE OF IMPENDING DEVELOPMENT/LONG RANGE DEVELOPMENT PLAN",
        "item_blurb": "",
        "subitem_number": "a",
        "subitem_title": "UC Santa Cruz Notice of Impending Development SCZ-NOID-0004-20 (Younger Lagoon Reserve Beach Public Access Management Plan, Santa Cruz). ",
        "subitem_blurb": "Public hearing and action on NOID by UC Santa Cruz pursuant to the certified LRDP to reauthorize the Younger Lagoon Reserve Beach Public Access Management Plan for the next 5 years, at UCSC\u2019s Marine Science Campus at Terrace Point, Santa Cruz, Santa Cruz County. (CB-SC)",
        "subitem_status": "Postponed"
    },
    {
        "date": "September 11, 2020",
        "district": "Central Coast District",
        "item_number": 11,
        "item_title": "New Appeals",
        "item_blurb": "",
        "subitem_number": "a",
        "subitem_title": "Appeal No. A-3-SCO-20-0027 (Sisney, Opal Cliffs, Santa Cruz Co.) ",
        "subitem_blurb": "Appeal by Commissioners Howell and Escalante and Surfrider Foundation of Santa Cruz County decision granting permit with conditions to Bret and Carol Sisney for demolition of approx. 6,000 sq.ft. single-story home and construction of new 2-story approx. 8,200 sq.ft. home and lap pool; and merger of two lots (out of four contiguous lots under common ownership) on blufftop, at 4660 Opal Cliff Dr. in unincorporated Opal Cliffs area of Santa Cruz County. (RG-SC)",
        "subitem_status": "SUBSTANTIAL ISSUE FOUND, de Novo Hearing CONTINUED"
    },
    {
        "date": "September 11, 2020",
        "district": "Central Coast District",
        "item_number": 12,
        "item_title": "Coastal Permit Applications",
        "item_blurb": "",
        "subitem_number": "a",
        "subitem_title": "Application No. 3-18-1230 (Port San Luis Repair and Maintenance, Avila Beach, San Luis Obispo Co.) ",
        "subitem_blurb": "Application of Port San Luis Harbor District to perform recurring repair and maintenance of District-owned facilities and infrastructure for next five years within District\u2019s boundaries in and around San Luis Bay, including Harford Pier, Harford Landing, Fisherman/Olde Port Beaches, Avila Beach, and Avila Pier, in unincorporated Avila Beach area of San Luis Obispo County. (AM-SC)",
        "subitem_status": "Approved with modification Special Condition 4b"
    },
    {
        "date": "September 11, 2020",
        "district": "North Coast District",
        "item_number": 13,
        "item_title": "Deputy Director's Report",
        "item_blurb": "Report by Deputy Director on permit waivers, emergency permits, immaterial amendments & extensions, and on comments from the public relating to the Deputy Director's report.  For specific information contact the Commission's Arcata office at (707) 826-8950.",
        "subitem_number": "",
        "subitem_title": "",
        "subitem_blurb": "",
        "subitem_status": ""
    },
    {
        "date": "September 11, 2020",
        "district": "Energy, Ocean Resources & Federal Consistency",
        "item_number": 14,
        "item_title": "Energy, Ocean Resources & Federal Consistency",
        "item_blurb": "Report by the Deputy Director on permit waivers, emergency permits, immaterial amendments & extensions, negative determinations, matters not requiring public hearings, and status report on offshore oil & gas exploration & development.  For specific information contact the Commission\u2019s Energy, Ocean Resources, and Federal Consistency Division office at (415) 904-5240.",
        "subitem_number": "",
        "subitem_title": "",
        "subitem_blurb": "",
        "subitem_status": ""
    },
    {
        "date": "September 11, 2020",
        "district": "Energy, Ocean Resources & Federal Consistency",
        "item_number": 15,
        "item_title": "Coastal Permit Applications",
        "item_blurb": "",
        "subitem_number": "a",
        "subitem_title": "Application No. 9-20-0268 (State Lands Commission, Santa Barbara Co.) ",
        "subitem_blurb": "Application of State Lands Commission to permanently re-abandon 4 leaking legacy oil wells in the subtidal and intertidal zone offshore Summerland, Santa Barbara County. (DG-SF) ",
        "subitem_status": "Moved to Consent Calendar, APPROVED WITH CONDITIONS"
    },
    {
        "date": "September 11, 2020",
        "district": "Energy, Ocean Resources & Federal Consistency",
        "item_number": 15,
        "item_title": "Coastal Permit Applications",
        "item_blurb": "",
        "subitem_number": "b",
        "subitem_title": "Application No. 9-20-0008 (San Diego Gas & Electric Company (SDGE), Camp Pendleton, San Diego Co.) ",
        "subitem_blurb": "Application of SDGE to replace existing wooden electricity transmission poles with steel poles, reconductor lines, and undertake pole-top construction along approx. 4.2 miles of existing utility line inland of Interstate-5, Marine Corps Base Camp Pendleton, San Diego County. (JW-SF)",
        "subitem_status": "Moved to Consent Calendar, APPROVED WITH CONDITIONS"
    },
    {
        "date": "September 11, 2020",
        "district": "Energy, Ocean Resources & Federal Consistency",
        "item_number": 16,
        "item_title": "Federal Consistency",
        "item_blurb": "",
        "subitem_number": "a",
        "subitem_title": "CD-0007-19 (Corps of Engineers, Los Angeles Co.) ",
        "subitem_blurb": "Consistency Determination by U.S. Army Corps of Engineers for East San Pedro Bay aquatic habitat enhancement project offshore of Long Beach, Los Angeles County. (AB-SF) ",
        "subitem_status": "Postponed"
    },
    {
        "date": "September 11, 2020",
        "district": "Enforcement",
        "item_number": 17,
        "item_title": "Enforcement Report",
        "item_blurb": "Report by Chief of Enforcement on Statewide Enforcement Program. (LAH-SF)",
        "subitem_number": "",
        "subitem_title": "",
        "subitem_blurb": "",
        "subitem_status": ""
    },
    {
        "date": "September 17, 2020",
        "district": "Statewide",
        "item_number": false,
        "item_title": "CANCELLED",
        "item_blurb": "",
        "subitem_number": "",
        "subitem_title": "",
        "subitem_blurb": "",
        "subitem_status": ""
    },
    {
        "date": "September 17, 2020",
        "district": "Statewide",
        "item_number": 1,
        "item_title": "CALL TO ORDER and ROLL CALL.",
        "item_blurb": "",
        "subitem_number": "",
        "subitem_title": "",
        "subitem_blurb": "",
        "subitem_status": ""
    },
    {
        "date": "September 17, 2020",
        "district": "Statewide",
        "item_number": 2,
        "item_title": "VIRTUAL MEETING PROCEDURES",
        "item_blurb": "",
        "subitem_number": "",
        "subitem_title": "",
        "subitem_blurb": "",
        "subitem_status": ""
    },
    {
        "date": "September 17, 2020",
        "district": "Energy, Ocean Resources and Federal Consistency",
        "item_number": false,
        "item_title": "CANCELLED <BR>Items Th3a and Th4a below will share a combined staff report and hearing",
        "item_blurb": "",
        "subitem_number": "",
        "subitem_title": "",
        "subitem_blurb": "",
        "subitem_status": ""
    },
    {
        "date": "September 17, 2020",
        "district": "Energy, Ocean Resources and Federal Consistency",
        "item_number": 3,
        "item_title": "New Appeals",
        "item_blurb": "",
        "subitem_number": "a",
        "subitem_title": "Appeal No. A-3-MRA-19-0034 (California American Water Company, et. al., Monterey Co.) ",
        "subitem_blurb": "Appeal by California American Water Company, Brian LeNeve, Castroville Community Services District, and Commissioners Howell and Uranga of City of Marina decision denying permit for construction and operation of well field, pipelines, and associated infrastructure at CEMEX sand mining facility, Lapis Road, Marina, Monterey County, to be used to provide source water for desalination facility located outside the coastal zone in Monterey County. (TL-SF)",
        "subitem_status": "Postponed"
    },
    {
        "date": "September 17, 2020",
        "district": "Energy, Ocean Resources and Federal Consistency",
        "item_number": 4,
        "item_title": "Coastal Permit Applications",
        "item_blurb": "",
        "subitem_number": "a",
        "subitem_title": "Application No. 9-19-0918 (California American Water Co., Seaside, Monterey Co.) ",
        "subitem_blurb": "Application of California American Water Company for consolidated permit to construct and operate water delivery pipelines and associated infrastructure within the City of Seaside, County of Monterey, and Commission\u2019s retained jurisdiction to support desalination facility located outside the coastal zone in Monterey County. (TL-SF)",
        "subitem_status": "Withdrawn"
    }
]